rampante/__init__.py
rampante/__version__.py
rampante/connector.py
rampante/decorator.py
rampante/scheduler.py
rampante/worker.py
rampante-0.0.14.dist-info/DESCRIPTION.rst
rampante-0.0.14.dist-info/METADATA
rampante-0.0.14.dist-info/RECORD
rampante-0.0.14.dist-info/WHEEL
rampante-0.0.14.dist-info/metadata.json
rampante-0.0.14.dist-info/top_level.txt
