Metadata-Version: 2.0
Name: rampante
Version: 0.0.14
Summary: A microservices nanoframework. 
Home-page: https://github.com/barrachri/rampante
Author: Christian Barra
Author-email: barrachri@gmail.com
License: Apache 2
Platform: UNKNOWN
Classifier: Development Status :: 4 - Beta
Classifier: Intended Audience :: Developers
Classifier: Framework :: AsyncIO
Classifier: License :: OSI Approved :: Apache Software License
Classifier: Programming Language :: Python
Classifier: Programming Language :: Python :: 3.6
Classifier: Programming Language :: Python :: Implementation :: CPython
Requires-Dist: tenacity (>=4.8.0)
Requires-Dist: asyncio-nats-streaming (>=0.1.2)
Requires-Dist: msgpack-python (>=0.4.8)
